fourier_laplace/__init__.py
fourier_laplace/drawer.py
fourier_laplace/tables/P_data.csv
fourier_laplace/tables/a_data.csv
fourier_laplace/tables/b_data.csv
fourier_laplace/tables/max_x_data.csv
fourier_laplace-1.0.4.dist-info/LICENSE
fourier_laplace-1.0.4.dist-info/METADATA
fourier_laplace-1.0.4.dist-info/WHEEL
fourier_laplace-1.0.4.dist-info/top_level.txt
fourier_laplace-1.0.4.dist-info/RECORD
