Metadata-Version: 2.1
Name: fourier-laplace
Version: 1.0.4
Summary: A method of quickly calculating point maps of axis-symmetric drops.
Author-email: Andres Hyer <andreshyer@gmail.com>
Project-URL: Homepage, https://github.com/andreshyer/fourier-laplace.git
Classifier: Development Status :: 5 - Production/Stable
Classifier: License :: OSI Approved :: GNU General Public License v3 (GPLv3)
Classifier: Programming Language :: Python :: 3
Requires-Python: >=3.0
License-File: LICENSE
Requires-Dist: numpy (>=1.0.0)
